XGRCpy/XGRCPowerBI.py
XGRCpy/XGRCpy.py
XGRCpy/__init__.py
XGRCpy-1.1.4.dist-info/METADATA
XGRCpy-1.1.4.dist-info/WHEEL
XGRCpy-1.1.4.dist-info/top_level.txt
XGRCpy-1.1.4.dist-info/RECORD
