Metadata-Version: 2.1
Name: XGRCpy
Version: 1.1.4
Summary: A package to decrypt and view XGRC table data
Author: Jacob O'Brien
Classifier: Programming Language :: Python :: 3
Classifier: License :: OSI Approved :: MIT License
Classifier: Operating System :: OS Independent
Requires-Python: >=3.6
Requires-Dist: requests
Requires-Dist: cryptography
Requires-Dist: requests-html
Requires-Dist: pandas
Requires-Dist: lxml-html-clean
